conductor/__init__.py
conductor/__main__.py
conductor/config.py
conductor/config_file.py
conductor/context.py
conductor/filename.py
conductor/task_identifier.py
conductor/cli/__init__.py
conductor/cli/archive.py
conductor/cli/clean.py
conductor/cli/gc.py
conductor/cli/restore.py
conductor/cli/run.py
conductor/cli/where.py
conductor/errors/__init__.py
conductor/errors/base.py
conductor/errors/generated.py
conductor/errors/signal.py
conductor/execution/__init__.py
conductor/execution/executor.py
conductor/execution/plan.py
conductor/execution/task.py
conductor/execution/task_state.py
conductor/execution/version_index.py
conductor/execution/version_index_queries.py
conductor/lib/__init__.py
conductor/lib/path.py
conductor/parsing/__init__.py
conductor/parsing/task_index.py
conductor/parsing/task_loader.py
conductor/parsing/validation.py
conductor/task_types/__init__.py
conductor/task_types/base.py
conductor/task_types/combine.py
conductor/task_types/group.py
conductor/task_types/raw.py
conductor/task_types/run.py
conductor/task_types/stdlib/__init__.py
conductor/task_types/stdlib/run_experiment_group.py
conductor/utils/__init__.py
conductor/utils/colored_output.py
conductor/utils/git.py
conductor/utils/output_handler.py
conductor/utils/run_arguments.py
conductor/utils/run_options.py
conductor/utils/sigchld.py
conductor/utils/tee.py
conductor/utils/time.py
conductor/utils/user_code.py
conductor_cli-0.7.0.dist-info/LICENSE
conductor_cli-0.7.0.dist-info/METADATA
conductor_cli-0.7.0.dist-info/WHEEL
conductor_cli-0.7.0.dist-info/entry_points.txt
conductor_cli-0.7.0.dist-info/top_level.txt
conductor_cli-0.7.0.dist-info/RECORD
