Metadata-Version: 2.1
Name: conductor-cli
Version: 0.7.0
Summary: A simple and elegant research computing orchestrator.
Home-page: https://www.geoffreyyu.com/conductor/
Author: Geoffrey Yu
Author-email: geoffxy@gmail.com
Maintainer: Geoffrey Yu
Maintainer-email: geoffxy@gmail.com
Keywords: research,experiment runner,research computing,experiment automation,orchestration
Classifier: Development Status :: 4 - Beta
Classifier: Intended Audience :: Developers
Classifier: License :: OSI Approved :: GNU Affero General Public License v3
Classifier: Programming Language :: Python :: 3 :: Only
Requires-Python: >=3.8
License-File: LICENSE
Requires-Dist: tomli
Provides-Extra: dev
Requires-Dist: black ; extra == 'dev'
Requires-Dist: mypy ; extra == 'dev'
Requires-Dist: pep517 ; extra == 'dev'
Requires-Dist: pylint ; extra == 'dev'
Requires-Dist: pytest ; extra == 'dev'
Requires-Dist: pytest-timeout ; extra == 'dev'
Requires-Dist: pyyaml ; extra == 'dev'
